flask_fingerprint/__init__.py
flask_fingerprint/helpers.py
Flask_Fingerprint-0.1.0.dist-info/LICENSE
Flask_Fingerprint-0.1.0.dist-info/METADATA
Flask_Fingerprint-0.1.0.dist-info/WHEEL
Flask_Fingerprint-0.1.0.dist-info/top_level.txt
Flask_Fingerprint-0.1.0.dist-info/RECORD
