Metadata-Version: 2.1
Name: Flask-Fingerprint
Version: 0.1.0
Summary: Flask extension for fingerprinting static assets
Home-page: https://codeberg.org/S1SYPHOS/flask-fingerprint
Author: Martin Folkers
Author-email: hello@twobrain.io
License: MIT
Project-URL: Issues, https://codeberg.org/S1SYPHOS/flask-fingerprint/issues
Platform: any
Classifier: Environment :: Web Environment
Classifier: Intended Audience :: Developers
Classifier: License :: OSI Approved :: MIT License
Classifier: Operating System :: OS Independent
Classifier: Programming Language :: Python :: 3
Classifier: Programming Language :: Python :: 3.7
Classifier: Programming Language :: Python :: 3.8
Classifier: Programming Language :: Python :: 3.9
Classifier: Programming Language :: Python :: 3.10
Classifier: Framework :: Flask
Classifier: Topic :: Internet :: WWW/HTTP :: Dynamic Content
Classifier: Topic :: Software Development :: Libraries :: Python Modules
Requires-Python: >= 3.7
License-File: LICENSE
Requires-Dist: flask
